README.rst
setup.cfg
setup.py
src/logcollection/__init__.py
src/logcollection/test_it.py
src/logcollection.egg-info/PKG-INFO
src/logcollection.egg-info/SOURCES.txt
src/logcollection.egg-info/dependency_links.txt
src/logcollection.egg-info/entry_points.txt
src/logcollection.egg-info/namespace_packages.txt
src/logcollection.egg-info/not-zip-safe
src/logcollection.egg-info/pbr.json
src/logcollection.egg-info/requires.txt
src/logcollection.egg-info/top_level.txt