Metadata-Version: 1.1
Name: logcollection
Version: 0-1-0
Summary: logging handler collection
Home-page: https://github.com/TakesxiSximada/logcollection
Author: TakesxiSximada
Author-email: takesxi.sximada@gmail.com
License: See http://www.python.org/3.4/license.html
Download-URL: https://github.com/TakesxiSximada/logcollection/archive/master.zip
Platform: any
Classifier: Development Status :: 1 - Planning
Classifier: Intended Audience :: Developers
Classifier: Intended Audience :: Information Technology
Classifier: Intended Audience :: System Administrators
Classifier: Natural Language :: English
Classifier: Operating System :: MacOS :: MacOS X
Classifier: Operating System :: Microsoft :: Windows
Classifier: Operating System :: POSIX
Classifier: Programming Language :: Python :: 2.7
Classifier: Programming Language :: Python :: 3.4
